seeclickfix/adapter.py
seeclickfix/client.py
seeclickfix/models/issue.py
seeclickfix/models/result.py
seeclickfix-0.3.dist-info/METADATA
seeclickfix-0.3.dist-info/WHEEL
seeclickfix-0.3.dist-info/RECORD
