Metadata-Version: 2.3
Name: seeclickfix
Version: 0.3
Summary: 
Author: Nate Shoffner
Author-email: nate.shoffner@gmail.com
Requires-Python: >=3.10
Classifier: Programming Language :: Python :: 3
Classifier: License :: OSI Approved :: MIT License
Classifier: Operating System :: OS Independent
Requires-Dist: aiohttp (>=3.9.1)
Requires-Dist: pydantic (>=2.11.5,<3.0.0)
Project-URL: Bug Tracker, https://github.com/NateShoffner/py-seeclickfix/issues
Project-URL: Homepage, https://github.com/NateShoffner/py-seeclickfix
